sidechainnet/__init__.py
sidechainnet/_version.py
sidechainnet/create.py
sidechainnet/dataloaders/ProteinBatch.py
sidechainnet/dataloaders/SCNDataset.py
sidechainnet/dataloaders/SCNProtein.py
sidechainnet/dataloaders/SimilarLengthBatchSampler.py
sidechainnet/dataloaders/__init__.py
sidechainnet/dataloaders/collate.py
sidechainnet/examples/__init__.py
sidechainnet/examples/alphabet_protein.py
sidechainnet/examples/losses.py
sidechainnet/examples/models.py
sidechainnet/examples/optim.py
sidechainnet/examples/sidechain_only_models.py
sidechainnet/examples/transformer.py
sidechainnet/examples/lightning/AnglePredictionHelper.py
sidechainnet/examples/lightning/LitSCNDataModule.py
sidechainnet/examples/lightning/LitSidechainDemo.py
sidechainnet/examples/lightning/LitSidechainTransformer.py
sidechainnet/examples/lightning/LoggingHelper.py
sidechainnet/examples/lightning/MyPLCallbacks.py
sidechainnet/research/log.py
sidechainnet/research/minimize_scn.py
sidechainnet/research/minimizer.py
sidechainnet/research/build_parameter_optim/build_params.pkl
sidechainnet/research/build_parameter_optim/optimize_build_params.py
sidechainnet/research/openfold/openfold_loss.py
sidechainnet/resources/all_proteinnet_ids.csv
sidechainnet/resources/amino12.lib
sidechainnet/resources/astral_data.txt
sidechainnet/resources/build_params.pkl
sidechainnet/resources/frcmod.ff14SB
sidechainnet/resources/full_protein_dssp_annotations.json
sidechainnet/resources/parm10.dat
sidechainnet/resources/single_domain_dssp_annotations.json
sidechainnet/structure/BatchedStructureBuilder.py
sidechainnet/structure/HydrogenBuilder.py
sidechainnet/structure/PdbBuilder.py
sidechainnet/structure/StructureBuilder.py
sidechainnet/structure/__init__.py
sidechainnet/structure/build_info.py
sidechainnet/structure/fastbuild.py
sidechainnet/structure/fastbuild_matrices.py
sidechainnet/structure/structure.py
sidechainnet/tests/__init__.py
sidechainnet/tests/test_build_info.py
sidechainnet/tests/test_create.py
sidechainnet-1.0.1.dist-info/LICENSE
sidechainnet-1.0.1.dist-info/METADATA
sidechainnet-1.0.1.dist-info/WHEEL
sidechainnet-1.0.1.dist-info/top_level.txt
sidechainnet-1.0.1.dist-info/RECORD
