Metadata-Version: 2.1
Name: sidechainnet
Version: 1.0.1
Summary: Tools and data for all-atom protein structure prediction via machine learning.
Home-page: https://github.com/jonathanking/sidechainnet
Author: Jonathan King
Author-email: jok120@pitt.edu
License: BSD-3-Clause
Platform: UNKNOWN
Classifier: Development Status :: 4 - Beta
Classifier: Intended Audience :: Science/Research
Classifier: License :: OSI Approved :: BSD License
Classifier: Programming Language :: Python :: 3
Classifier: Operating System :: POSIX :: Linux
Classifier: Topic :: Scientific/Engineering :: Artificial Intelligence
Classifier: Topic :: Scientific/Engineering :: Bio-Informatics
Requires-Python: >=3.5
License-File: LICENSE
Requires-Dist: ProDy (>=2.0)
Requires-Dist: numpy
Requires-Dist: scipy
Requires-Dist: torch (>=1.7)
Requires-Dist: biopython
Requires-Dist: tqdm
Requires-Dist: py3Dmol
Requires-Dist: requests
Requires-Dist: setuptools
Requires-Dist: pandas
